LICENSE.md
MANIFEST.in
README.md
setup.py
admin_soft/__init__.py
admin_soft/admin.py
admin_soft/apps.py
admin_soft/forms.py
admin_soft/models.py
admin_soft/tests.py
admin_soft/urls.py
admin_soft/utils.py
admin_soft/views.py
admin_soft/static/assets/css/forms.css
admin_soft/static/assets/css/nucleo-icons.css
admin_soft/static/assets/css/nucleo-svg.css
admin_soft/static/assets/css/soft-ui-dashboard.css
admin_soft/static/assets/css/soft-ui-dashboard.css.map
admin_soft/static/assets/css/soft-ui-dashboard.min.css
admin_soft/static/assets/css/widgets.css
admin_soft/static/assets/fonts/nucleo-icons.eot
admin_soft/static/assets/fonts/nucleo-icons.svg
admin_soft/static/assets/fonts/nucleo-icons.ttf
admin_soft/static/assets/fonts/nucleo-icons.woff
admin_soft/static/assets/fonts/nucleo-icons.woff2
admin_soft/static/assets/fonts/nucleo.eot
admin_soft/static/assets/fonts/nucleo.ttf
admin_soft/static/assets/fonts/nucleo.woff
admin_soft/static/assets/fonts/nucleo.woff2
admin_soft/static/assets/images/icon-calendar.svg
admin_soft/static/assets/images/icon-clock.svg
admin_soft/static/assets/images/icon-unknown-alt.svg
admin_soft/static/assets/images/icon-unknown.svg
admin_soft/static/assets/images/search.svg
admin_soft/static/assets/images/selector-icons.svg
admin_soft/static/assets/img/apple-icon.png
admin_soft/static/assets/img/bg1.jpg
admin_soft/static/assets/img/bruce-mars.jpg
admin_soft/static/assets/img/down-arrow-dark.svg
admin_soft/static/assets/img/down-arrow-white.svg
admin_soft/static/assets/img/down-arrow.svg
admin_soft/static/assets/img/favicon.png
admin_soft/static/assets/img/home-decor-1.jpg
admin_soft/static/assets/img/home-decor-2.jpg
admin_soft/static/assets/img/home-decor-3.jpg
admin_soft/static/assets/img/ivana-square.jpg
admin_soft/static/assets/img/ivancik.jpg
admin_soft/static/assets/img/kal-visuals-square.jpg
admin_soft/static/assets/img/logo-ct-dark.png
admin_soft/static/assets/img/logo-ct.png
admin_soft/static/assets/img/marie.jpg
django_admin_soft_dashboard.egg-info/PKG-INFO
django_admin_soft_dashboard.egg-info/SOURCES.txt
django_admin_soft_dashboard.egg-info/dependency_links.txt
django_admin_soft_dashboard.egg-info/not-zip-safe
django_admin_soft_dashboard.egg-info/top_level.txt
